Workbook
Name Aporte_mensal: Predix!$C$19
Name Capacidade_Total_Investimento: Predix!$G$14
Name Despesas: Predix!$C$15
Name Dividendos_carteira: Predix!$C$16
Name Patrimonio: Predix!$C$22
Name qtd_anos: Predix!$C$20
Name Renda_total: Predix!$C$14
Name Taxa_mensal: Predix!$C$21

Sheet Predix
B13: Personalizar | E13: Capacidade de Investimento Mensal
B14: Renda Total (mensal) | C14: 9000 | E14: Capacidade de Investimento Total | G14: =Renda_total-Despesas -> 7000
B15: Despesas Totais (mensal) | C15: 2000 | E15: Índice de Poupança % | G15: =Capacidade_Total_Investimento/Renda_total -> 0.77777778
B16: Dividendos da Carteira | C16: 0.01 | E16: Sugestão Padrão de Investimento | G16: =Renda_total*30% -> 2700
B18: Investimento Mensal | E18: Previsões de Retorno | G18: Dividendos Mensais
B19: Aporte | C19: 7000 | E19: 2 anos | F19: =FV($C$21,$A33*12,-$C$19) -> 188814.25 | G19: =F19*Dividendos_carteira -> 1888.1425
B20: Quantidade de Anos | C20: 5 | E20: 5 anos | F20: =FV($C$21,$A34*12,-$C$19) -> 571687.69 | G20: =F20*Dividendos_carteira -> 5716.8769
B21: Taxa de Rendimento (mensal) | C21: 0.01 | E21: 10 anos | F21: =FV($C$21,$A35*12,-$C$19) -> 1610270.8 | G21: =F21*Dividendos_carteira -> 16102.708
B22: Patrimônio Acumulado | C22: =FV(Taxa_mensal,qtd_anos*12,-Aporte_mensal) -> 571687.69 | E22: 20 anos | F22: =FV($C$21,$A36*12,-$C$19) -> 6924787.6 | G22: =F22*Dividendos_carteira -> 69247.876
B23: Dividendos Mensais | C23: =C22*Dividendos_carteira -> 5716.8769 | E23: 30 anos | F23: =FV($C$21,$A37*12,-$C$19) -> 24464749 | G23: =F23*Dividendos_carteira -> 244647.49
B25: PERFIL INVESTIDOR | E25: Conservador
B26: Valor Mensal Aportado | E26: =Aporte_mensal -> 7000
B28: Classes de Investimento | E28: Percentual de Alocação | G28: Valores
B29: Renda Fixa | E29: =VLOOKUP($E$25&"-"&B29,'Configuracao _Perfil_Investidor'!A3:D9,4,FALSE) -> 0.8 | G29: =$E$26*E29 -> 5600
B30: Renda Variável | E30: =VLOOKUP($E$25&"-"&B30,'Configuracao _Perfil_Investidor'!A4:D10,4,FALSE) -> 0.2 | G30: =$E$26*E30 -> 1400
B31: Total | E31: =SUM(E29:F30) -> 1 | G31: =SUM(G29:G30) -> 7000
A33: 2 | B33: ALOCAÇÃO POR TIPO DE FII | E33: =$E$25 -> Conservador
A34: 5 | B34: % da Renda Variável destinada a FIIs | E34: 1
A35: 10 | B35: Valor destinado a FIIs | E35: =$G$30*$E$34 -> 1400
A36: 20
A37: 30 | B37: Tipo de FII | E37: Percentual de Alocação | G37: Valores
B38: Tijolo | E38: =VLOOKUP($E$25&"-"&B38,'Configuracao _Perfil_Investidor'!$F$4:$I$18,4,FALSE) -> 0.3 | G38: =$E$35*E38 -> 420
B39: Papel | E39: =VLOOKUP($E$25&"-"&B39,'Configuracao _Perfil_Investidor'!$F$4:$I$18,4,FALSE) -> 0.35 | G39: =$E$35*E39 -> 490
B40: FOFs | E40: =VLOOKUP($E$25&"-"&B40,'Configuracao _Perfil_Investidor'!$F$4:$I$18,4,FALSE) -> 0.2 | G40: =$E$35*E40 -> 280
B41: Desenvolvimento | E41: =VLOOKUP($E$25&"-"&B41,'Configuracao _Perfil_Investidor'!$F$4:$I$18,4,FALSE) -> 0 | G41: =$E$35*E41 -> 0
B42: Híbrido | E42: =VLOOKUP($E$25&"-"&B42,'Configuracao _Perfil_Investidor'!$F$4:$I$18,4,FALSE) -> 0.15 | G42: =$E$35*E42 -> 210
B43: Total | E43: =SUM(E38:E42) -> 1 | G43: =SUM(G38:G42) -> 1400

Sheet Configuracao _Perfil_Investidor
A3: Chave | B3: Perfil Investidor | C3: Classes de Investimento | D3: % | F3: Chave | G3: Perfil Investidor | H3: Tipo de FII | I3: %
A4: =B4&"-"&C4 -> Conservador-Renda Fixa | B4: Conservador | C4: Renda Fixa | D4: 0.8 | F4: =G4&"-"&H4 -> Conservador-Tijolo | G4: Conservador | H4: Tijolo | I4: 0.3
A5: =B5&"-"&C5 -> Conservador-Renda Variável | B5: Conservador | C5: Renda Variável | D5: 0.2 | F5: =G5&"-"&H5 -> Conservador-Papel | G5: Conservador | H5: Papel | I5: 0.35
A6: =B6&"-"&C6 -> Moderado-Renda Fixa | B6: Moderado | C6: Renda Fixa | D6: 0.6 | F6: =G6&"-"&H6 -> Conservador-FOFs | G6: Conservador | H6: FOFs | I6: 0.2
A7: =B7&"-"&C7 -> Moderado-Renda Variável | B7: Moderado | C7: Renda Variável | D7: 0.4 | F7: =G7&"-"&H7 -> Conservador-Desenvolvimento | G7: Conservador | H7: Desenvolvimento | I7: 0
A8: =B8&"-"&C8 -> Agressivo-Renda Fixa | B8: Agressivo | C8: Renda Fixa | D8: 0.5 | F8: =G8&"-"&H8 -> Conservador-Híbrido | G8: Conservador | H8: Híbrido | I8: 0.15
A9: =B9&"-"&C9 -> Agressivo-Renda Variável | B9: Agressivo | C9: Renda Variável | D9: 0.5 | F9: =G9&"-"&H9 -> Moderado-Tijolo | G9: Moderado | H9: Tijolo | I9: 0.35
F10: =G10&"-"&H10 -> Moderado-Papel | G10: Moderado | H10: Papel | I10: 0.3
F11: =G11&"-"&H11 -> Moderado-FOFs | G11: Moderado | H11: FOFs | I11: 0.15
F12: =G12&"-"&H12 -> Moderado-Desenvolvimento | G12: Moderado | H12: Desenvolvimento | I12: 0.05
F13: =G13&"-"&H13 -> Moderado-Híbrido | G13: Moderado | H13: Híbrido | I13: 0.15
F14: =G14&"-"&H14 -> Agressivo-Tijolo | G14: Agressivo | H14: Tijolo | I14: 0.35
F15: =G15&"-"&H15 -> Agressivo-Papel | G15: Agressivo | H15: Papel | I15: 0.2
F16: =G16&"-"&H16 -> Agressivo-FOFs | G16: Agressivo | H16: FOFs | I16: 0.1
F17: =G17&"-"&H17 -> Agressivo-Desenvolvimento | G17: Agressivo | H17: Desenvolvimento | I17: 0.2
F18: =G18&"-"&H18 -> Agressivo-Híbrido | G18: Agressivo | H18: Híbrido | I18: 0.15

Sheet Grafico_Alocacao_dados
A1: Classe | B1: Alocação | D1: Tipo de FII | E1: Percentual de Alocação
A2: =Predix!B29 -> Renda Fixa | B2: =Predix!E29 -> 0.8 | D2: Tijolo | E2: 0.3
A3: =Predix!B30 -> Renda Variável | B3: =Predix!E30 -> 0.2 | D3: Papel | E3: 0.35
D4: FOFs | E4: 0.2
D5: Desenvolvimento | E5: 0
D6: Híbrido | E6: 0.15
